marx/__init__.py
marx/cli.py
marx/config.py
marx/docker_runner.py
marx/exceptions.py
marx/github.py
marx/review.py
marx/ui.py
marx/prompts/__init__.py
marx/prompts/dedup_prompt.md
marx/prompts/review_prompt.md
marx_ai-0.1.8.dist-info/licenses/LICENSE
marx_ai-0.1.8.dist-info/METADATA
marx_ai-0.1.8.dist-info/WHEEL
marx_ai-0.1.8.dist-info/entry_points.txt
marx_ai-0.1.8.dist-info/top_level.txt
marx_ai-0.1.8.dist-info/RECORD
