Metadata-Version: 2.4
Name: marx-ai
Version: 0.1.8
Summary: Automated multi-agent code review tool for GitHub PRs
Author: Marx Contributors
License-Expression: MIT
Project-URL: Homepage, https://github.com/forketyfork/marx
Project-URL: Repository, https://github.com/forketyfork/marx
Project-URL: Issues, https://github.com/forketyfork/marx/issues
Classifier: Programming Language :: Python :: 3
Classifier: Programming Language :: Python :: 3.12
Classifier: Operating System :: OS Independent
Requires-Python: >=3.12
License-File: LICENSE
Requires-Dist: click>=8.1.0
Requires-Dist: rich>=13.7.0
Requires-Dist: docker>=7.0.0
Requires-Dist: pydantic>=2.5.0
Provides-Extra: dev
Requires-Dist: pytest>=7.4.0; extra == "dev"
Requires-Dist: pytest-cov>=4.1.0; extra == "dev"
Requires-Dist: pytest-asyncio>=0.21.0; extra == "dev"
Requires-Dist: black>=23.12.0; extra == "dev"
Requires-Dist: ruff>=0.1.9; extra == "dev"
Requires-Dist: mypy>=1.8.0; extra == "dev"
Dynamic: license-file
